Metadata-Version: 1.0
Name: ziti
Version: 0.1.0
Summary: Ziti fabric client for Python programs
Home-page: https://support.netfoundry.io/
Author: NetFoundry
Author-email: support@netfoundry.io
License: MIT
Platform: UNKNOWN
